setup.py
from_m3u8_get_mp4/__init__.py
from_m3u8_get_mp4/decrypt_video.py
from_m3u8_get_mp4/detect_moudle.py
from_m3u8_get_mp4/get_video.py
from_m3u8_get_mp4/settings.py
from_m3u8_get_mp4.egg-info/PKG-INFO
from_m3u8_get_mp4.egg-info/SOURCES.txt
from_m3u8_get_mp4.egg-info/dependency_links.txt
from_m3u8_get_mp4.egg-info/top_level.txt